pyrgo/__init__.py
pyrgo/__main__.py
pyrgo/command_exec.py
pyrgo/conf.py
pyrgo/py.typed
pyrgo/typing.py
pyrgo/utils.py
pyrgo/cmds/__init__.py
pyrgo/cmds/add.py
pyrgo/cmds/audit.py
pyrgo/cmds/build.py
pyrgo/cmds/check.py
pyrgo/cmds/clean.py
pyrgo/cmds/doc.py
pyrgo/cmds/fix.py
pyrgo/cmds/fmt.py
pyrgo/cmds/lock.py
pyrgo/cmds/new.py
pyrgo/cmds/remove.py
pyrgo/cmds/sync.py
pyrgo/cmds/test.py
pyrgo/resources/__init__.py
pyrgo/resources/new-project/README.md
pyrgo/resources/new-project/pyproject.toml
pyrgo/resources/new-project/new_project/__init__.py
pyrgo/resources/new-project/tests/test_something.py
pyrgo-2.2.13.dist-info/METADATA
pyrgo-2.2.13.dist-info/WHEEL
pyrgo-2.2.13.dist-info/entry_points.txt
pyrgo-2.2.13.dist-info/licenses/LICENSE
pyrgo-2.2.13.dist-info/RECORD
