Metadata-Version: 2.3
Name: pyrgo
Version: 2.2.13
Project-URL: Documentation, https://github.com/Tomperez98/pyrgo#readme
Project-URL: Issues, https://github.com/Tomperez98/pyrgo/issues
Project-URL: Source, https://github.com/Tomperez98/pyrgo
Author-email: Tomas Perez Alvarez <tomasperezalvarez@gmail.com>
License-File: LICENSE
Classifier: Programming Language :: Python :: Implementation :: CPython
Classifier: Programming Language :: Python :: Implementation :: PyPy
Classifier: Programming Language :: Rust
Requires-Python: >=3.9
Requires-Dist: build<2
Requires-Dist: click<9
Requires-Dist: mashumaro[orjson,toml]<4
Requires-Dist: mypy<2
Requires-Dist: pdoc<15
Requires-Dist: pip-audit<3
Requires-Dist: pytest<8
Requires-Dist: result<1
Requires-Dist: ruff<1,>=0.3.0
Requires-Dist: tomlkit<1
Requires-Dist: uv<1,>=0.1.5
Requires-Dist: vulture<3
Provides-Extra: dev
Requires-Dist: pytest-cov<5; extra == 'dev'
Requires-Dist: types-toml; extra == 'dev'
